codethecity_slackbot-1.0.0.dev3.dist-info/DESCRIPTION.rst
codethecity_slackbot-1.0.0.dev3.dist-info/entry_points.txt
codethecity_slackbot-1.0.0.dev3.dist-info/METADATA
codethecity_slackbot-1.0.0.dev3.dist-info/metadata.json
codethecity_slackbot-1.0.0.dev3.dist-info/RECORD
codethecity_slackbot-1.0.0.dev3.dist-info/top_level.txt
codethecity_slackbot-1.0.0.dev3.dist-info/WHEEL
slackbot/__init__.py
slackbot/slackbot.py
