Metadata-Version: 2.0
Name: codethecity-slackbot
Version: 1.0.0.dev3
Summary: A framework for creating Slackbots for Python. Developed for CodeTheCity.
Home-page: https://github.com/andrewsage/slackbot
Author: Andrew Sage
Author-email: andrew@codethecity.org
License: MIT
Keywords: slack bot development
Platform: UNKNOWN
Classifier: Development Status :: 3 - Alpha
Classifier: Intended Audience :: Developers
Classifier: Topic :: Communications :: Chat
Classifier: License :: OSI Approved :: MIT License
Classifier: Programming Language :: Python :: 2
Classifier: Programming Language :: Python :: 2.6
Classifier: Programming Language :: Python :: 2.7
Classifier: Programming Language :: Python :: 3
Classifier: Programming Language :: Python :: 3.3
Classifier: Programming Language :: Python :: 3.4
Classifier: Programming Language :: Python :: 3.5
Requires-Dist: slackclient
Requires-Dist: eventbrite
Provides-Extra: dev
Requires-Dist: check-manifest; extra == 'dev'
Provides-Extra: test
Requires-Dist: coverage; extra == 'test'
